logrot_tool/__init__.py
logrot_tool/main.py
logrot_tool-1.0.0.dist-info/METADATA
logrot_tool-1.0.0.dist-info/WHEEL
logrot_tool-1.0.0.dist-info/entry_points.txt
logrot_tool-1.0.0.dist-info/top_level.txt
logrot_tool-1.0.0.dist-info/RECORD
